[
  {
    "l": 370,
    "w": 220,
    "h": 170
  },
  {
    "l": 200,
    "w": 310,
    "h": 160
  },
  {
    "l": 170,
    "w": 660,
    "h": 170
  },
  {
    "l": 190,
    "w": 780,
    "h": 190
  },
  {
    "l": 330,
    "w": 310,
    "h": 150
  },
  {
    "l": 320,
    "w": 760,
    "h": 160
  },
  {
    "l": 330,
    "w": 770,
    "h": 150
  },
  {
    "l": 220,
    "w": 750,
    "h": 220
  },
  {
    "l": 270,
    "w": 200,
    "h": 190
  },
  {
    "l": 750,
    "w": 780,
    "h": 180
  },
  {
    "l": 160,
    "w": 290,
    "h": 150
  },
  {
    "l": 160,
    "w": 540,
    "h": 160
  },
  {
    "l": 150,
    "w": 290,
    "h": 150
  },
  {
    "l": 260,
    "w": 180,
    "h": 160
  },
  {
    "l": 260,
    "w": 570,
    "h": 170
  },
  {
    "l": 360,
    "w": 190,
    "h": 160
  },
  {
    "l": 360,
    "w": 190,
    "h": 190
  },
  {
    "l": 200,
    "w": 680,
    "h": 190
  },
  {
    "l": 290,
    "w": 700,
    "h": 190
  },
  {
    "l": 210,
    "w": 560,
    "h": 190
  },
  {
    "l": 690,
    "w": 750,
    "h": 370
  },
  {
    "l": 270,
    "w": 440,
    "h": 190
  },
  {
    "l": 170,
    "w": 770,
    "h": 150
  },
  {
    "l": 270,
    "w": 400,
    "h": 170
  },
  {
    "l": 190,
    "w": 520,
    "h": 190
  }
]