[
  {
    "l": 590,
    "w": 480,
    "h": 470
  },
  {
    "l": 580,
    "w": 480,
    "h": 470
  },
  {
    "l": 600,
    "w": 480,
    "h": 470
  },
  {
    "l": 240,
    "w": 450,
    "h": 190
  },
  {
    "l": 190,
    "w": 380,
    "h": 190
  },
  {
    "l": 190,
    "w": 430,
    "h": 190
  },
  {
    "l": 500,
    "w": 480,
    "h": 470
  },
  {
    "l": 280,
    "w": 410,
    "h": 190
  },
  {
    "l": 600,
    "w": 470,
    "h": 470
  },
  {
    "l": 150,
    "w": 380,
    "h": 150
  },
  {
    "l": 200,
    "w": 400,
    "h": 190
  },
  {
    "l": 270,
    "w": 340,
    "h": 190
  },
  {
    "l": 190,
    "w": 340,
    "h": 190
  },
  {
    "l": 470,
    "w": 510,
    "h": 470
  },
  {
    "l": 200,
    "w": 510,
    "h": 190
  },
  {
    "l": 300,
    "w": 510,
    "h": 190
  },
  {
    "l": 310,
    "w": 510,
    "h": 190
  }
]