[
  {
    "l": 630,
    "w": 770,
    "h": 270
  },
  {
    "l": 560,
    "w": 420,
    "h": 350
  },
  {
    "l": 530,
    "w": 780,
    "h": 250
  },
  {
    "l": 610,
    "w": 770,
    "h": 230
  },
  {
    "l": 620,
    "w": 770,
    "h": 350
  },
  {
    "l": 750,
    "w": 750,
    "h": 620
  },
  {
    "l": 720,
    "w": 540,
    "h": 390
  },
  {
    "l": 780,
    "w": 760,
    "h": 650
  },
  {
    "l": 780,
    "w": 770,
    "h": 360
  },
  {
    "l": 600,
    "w": 480,
    "h": 330
  },
  {
    "l": 240,
    "w": 410,
    "h": 170
  },
  {
    "l": 490,
    "w": 710,
    "h": 200
  },
  {
    "l": 700,
    "w": 300,
    "h": 150
  },
  {
    "l": 740,
    "w": 600,
    "h": 280
  }
]